est/__init__.py
est/filters.py
est/obs.py
opt/__init__.py
opt/debug.py
opt/mpc/__init__.py
opt/mpc/mpc.py
opt/mpc/nlp.py
opt/mpc/ocp.py
nlpopt-0.0.16.dist-info/METADATA
nlpopt-0.0.16.dist-info/WHEEL
nlpopt-0.0.16.dist-info/top_level.txt
nlpopt-0.0.16.dist-info/RECORD
