Metadata-Version: 2.1
Name: nlpopt
Version: 0.0.16
Summary: A numerical package for optimization
Home-page: UNKNOWN
Author: Johannes P. Maree
Author-email: phillip.maree@sintef.no
License: UNKNOWN
Platform: UNKNOWN
